setup.py
GxDoxybook.egg-info/PKG-INFO
GxDoxybook.egg-info/SOURCES.txt
GxDoxybook.egg-info/dependency_links.txt
GxDoxybook.egg-info/entry_points.txt
GxDoxybook.egg-info/requires.txt
GxDoxybook.egg-info/top_level.txt
doxybook/__init__.py
doxybook/__main__.py
doxybook/cache.py
doxybook/constants.py
doxybook/doxygen.py
doxybook/genbook.py
doxybook/generator.py
doxybook/main.py
doxybook/markdown.py
doxybook/node.py
doxybook/property.py
doxybook/runner.py
doxybook/update.py
doxybook/utils.py
doxybook/xml_parser.py
doxybook/templates/__init__.py
doxybook/templates/annotated.py
doxybook/templates/classes.py
doxybook/templates/definelist.py
doxybook/templates/enum.py
doxybook/templates/enumlist.py
doxybook/templates/files.py
doxybook/templates/function.py
doxybook/templates/functionlist.py
doxybook/templates/hierarchy.py
doxybook/templates/index.py
doxybook/templates/member.py
doxybook/templates/member_definition.py
doxybook/templates/member_table.py
doxybook/templates/modules.py
doxybook/templates/namespaces.py
doxybook/templates/page.py
doxybook/templates/pages.py
doxybook/templates/programlisting.py
doxybook/templates/typedeflist.py