Metadata-Version: 1.0
Name: GxDoxybook
Version: 1.0.7
Summary: Convert C annotation to gitbook
Home-page: UNKNOWN
Author: zhaobk
Author-email: zhaobk@nationalchip.com
License: UNKNOWN
Keywords: c annotation gitbook
Platform: UNKNOWN
